aiomessenger/__init__.py
aiomessenger/client.py
aiomessenger/tests/__init__.py
aiomessenger/tests/test_client.py
aiomessenger/tests/test_dummy.py
aiomessenger-0.2.1.dist-info/LICENSE
aiomessenger-0.2.1.dist-info/METADATA
aiomessenger-0.2.1.dist-info/WHEEL
aiomessenger-0.2.1.dist-info/top_level.txt
aiomessenger-0.2.1.dist-info/RECORD
