Metadata-Version: 2.1
Name: aiomessenger
Version: 0.2.1
Summary: # aiomessenger
